core/__init__.py
core/base.py
core/drawer.py
core/header.py
core/left_panel.py
core/middle_panel.py
core/mobile_drop_down.py
core/mobile_navigation.py
core/navigation.py
core/repo_data.py
core/right_panel.py
fx_material/__init__.py
fx_material/annotation.py
fx_material/block.py
fx_material/typography.py
scripts/__init__.py
scripts/build.py
scripts/create.py
utilities/__init__.py
utilities/fx_cli.py
utilities/fx_config.py
utilities/fx_error.py
utilities/fx_main.py
utilities/fx_scratch.py
utilities/fx_sub_router.py
utilities/fx_sub_template.py
utilities/fx_template.py
Fletxible-0.7.1.dist-info/LICENSE
Fletxible-0.7.1.dist-info/METADATA
Fletxible-0.7.1.dist-info/WHEEL
Fletxible-0.7.1.dist-info/entry_points.txt
Fletxible-0.7.1.dist-info/top_level.txt
Fletxible-0.7.1.dist-info/RECORD
