Metadata-Version: 2.1
Name: Fletxible
Version: 0.7.1
Summary: Web Boilerplate for Flet Library
Home-page: https://github.com/LineIndent/fletxible
Author: S. Ahmad P. Hakimi
Author-email: pourhakimi@pm.me
Keywords: python web template,web application,theme
Classifier: Programming Language :: Python :: 3
Classifier: License :: OSI Approved :: MIT License
Classifier: Operating System :: OS Independent
License-File: LICENSE
Requires-Dist: click (>=8.1.3)
Requires-Dist: flet (>=0.9.0)
Requires-Dist: beautifulsoup4 (>=4.12.2)
